{
  "project_info": {
    "project_number": "879863435160",
    "project_id": "android-tracker-95e88",
    "storage_bucket": "android-tracker-95e88.firebasestorage.app"
  },
  "client": [
    {
      "client_info": {
        "mobilesdk_app_id": "1:879863435160:android:eff87876dfd1777604a5ed",
        "android_client_info": {
          "package_name": "kaist.iclab.trackerSystem"
        }
      },
      "oauth_client": [
        {
          "client_id": "879863435160-hq8jgje8iq80b64r2g502rroftu58uv7.apps.googleusercontent.com",
          "client_type": 1,
          "android_info": {
            "package_name": "kaist.iclab.trackerSystem",
            "certificate_hash": "4baa71fed572ef194f50953a8d2ecd91e0c16f3a"
          }
        },
        {
          "client_id": "879863435160-qn3fc5fmlvtr9itp1rep4c05ou3rdjdj.apps.googleusercontent.com",
          "client_type": 3
        }
      ],
      "api_key": [
        {
          "current_key": "AIzaSyBXOTOS6FyFnnWcBJpW2KnGV7opr7az8Ok"
        }
      ],
      "services": {
        "appinvite_service": {
          "other_platform_oauth_client": [
            {
              "client_id": "879863435160-qn3fc5fmlvtr9itp1rep4c05ou3rdjdj.apps.googleusercontent.com",
              "client_type": 3
            }
          ]
        }
      }
    }
  ],
  "configuration_version": "1"
}